django_snakeviz_profiling/__about__.py
django_snakeviz_profiling/__init__.py
django_snakeviz_profiling/db_profile.py
django_snakeviz_profiling/static/django_snakeviz_profiling/LICENSE.txt
django_snakeviz_profiling/static/django_snakeviz_profiling/drawsvg.js
django_snakeviz_profiling/static/django_snakeviz_profiling/favicon.ico
django_snakeviz_profiling/static/django_snakeviz_profiling/snakeviz.css
django_snakeviz_profiling/static/django_snakeviz_profiling/snakeviz.js
django_snakeviz_profiling/static/django_snakeviz_profiling/sunburst.js
django_snakeviz_profiling/static/django_snakeviz_profiling/images/sort_asc.png
django_snakeviz_profiling/static/django_snakeviz_profiling/images/sort_both.png
django_snakeviz_profiling/static/django_snakeviz_profiling/images/sort_desc.png
django_snakeviz_profiling/static/django_snakeviz_profiling/vendor/d3.min.js
django_snakeviz_profiling/static/django_snakeviz_profiling/vendor/d3.v3.min.js
django_snakeviz_profiling/static/django_snakeviz_profiling/vendor/immutable.min.js
django_snakeviz_profiling/static/django_snakeviz_profiling/vendor/jquery-1.11.1.min.js
django_snakeviz_profiling/static/django_snakeviz_profiling/vendor/jquery-3.2.1.min.js
django_snakeviz_profiling/static/django_snakeviz_profiling/vendor/jquery.dataTables.min.css
django_snakeviz_profiling/static/django_snakeviz_profiling/vendor/jquery.dataTables.min.js
django_snakeviz_profiling/static/django_snakeviz_profiling/vendor/lodash.compat.min.js
django_snakeviz_profiling/static/django_snakeviz_profiling/vendor/lodash.min.js
django_snakeviz_profiling/templates/django_snakeviz_profiling/viz.html
django_snakeviz_profiling-0.1.0.dist-info/METADATA
django_snakeviz_profiling-0.1.0.dist-info/WHEEL
django_snakeviz_profiling-0.1.0.dist-info/licenses/LICENSE.txt
django_snakeviz_profiling-0.1.0.dist-info/RECORD
