Metadata-Version: 2.1
Name: django-snakeviz-profiling
Version: 0.1.0
Summary: Integrate snakeviz profile visualization into django
Project-URL: Documentation, https://github.com/rgeoghegan/django-snakeviz-profiling#readme
Project-URL: Issues, https://github.com/rgeoghegan/django-snakeviz-profiling/issues
Project-URL: Source, https://github.com/rgeoghegan/django-snakeviz-profiling
Author-email: Rory Geoghegan <r.geoghegan@gmail.com>
License-Expression: MIT
License-File: LICENSE.txt
Classifier: Development Status :: 4 - Beta
Classifier: Framework :: Django
Classifier: Programming Language :: Python
Classifier: Programming Language :: Python :: 3.7
Classifier: Programming Language :: Python :: 3.8
Classifier: Programming Language :: Python :: 3.9
Classifier: Programming Language :: Python :: 3.10
Classifier: Programming Language :: Python :: 3.11
Classifier: Programming Language :: Python :: Implementation :: CPython
Classifier: Programming Language :: Python :: Implementation :: PyPy
Classifier: Topic :: Software Development
Requires-Python: >=3.7
Requires-Dist: django>=4.0
Requires-Dist: snakeviz>=2.2
